dbusCExtension.cpython-37m-arm-linux-gnueabihf.so
wirepas_gateway/__about__.py
wirepas_gateway/__init__.py
wirepas_gateway/__main__.py
wirepas_gateway/configure_node.py
wirepas_gateway/dbus_print_client.py
wirepas_gateway/transport_service.py
wirepas_gateway/dbus/__init__.py
wirepas_gateway/dbus/dbus_client.py
wirepas_gateway/dbus/return_code.py
wirepas_gateway/dbus/sink_manager.py
wirepas_gateway/dbus/c-extension/dbus_c.c
wirepas_gateway/protocol/__init__.py
wirepas_gateway/protocol/mqtt_wrapper.py
wirepas_gateway/protocol/topic_helper.py
wirepas_gateway/utils/__init__.py
wirepas_gateway/utils/argument_tools.py
wirepas_gateway/utils/log_tools.py
wirepas_gateway/utils/serialization_tools.py
wirepas_gateway-1.3.1.data/data/wirepas_gateway-extras/package/LICENSE
wirepas_gateway-1.3.1.data/data/wirepas_gateway-extras/package/README.md
wirepas_gateway-1.3.1.data/data/wirepas_gateway-extras/package/requirements.txt
wirepas_gateway-1.3.1.data/data/wirepas_gateway-extras/package/setup.py
wirepas_gateway-1.3.1.dist-info/LICENSE
wirepas_gateway-1.3.1.dist-info/METADATA
wirepas_gateway-1.3.1.dist-info/WHEEL
wirepas_gateway-1.3.1.dist-info/entry_points.txt
wirepas_gateway-1.3.1.dist-info/top_level.txt
wirepas_gateway-1.3.1.dist-info/RECORD
