Metadata-Version: 2.1
Name: wirepas-gateway
Version: 1.3.1
Summary: Wirepas gateway transport service that connects the local dbus to a remote MQTT broker.
Home-page: https://github.com/wirepas/gateway
Author: Wirepas Ltd
Author-email: opensource@wirepas.com
License: Apache-2
Keywords: wirepas connectivity iot mesh
Platform: UNKNOWN
Classifier: Development Status :: 5 - Production/Stable
Classifier: Intended Audience :: Developers
Classifier: License :: OSI Approved :: Apache Software License
Classifier: Topic :: Software Development :: Libraries
Classifier: Programming Language :: Python :: 3
Requires-Python: >=3.7
Requires-Dist: PyYAML (==5.1.2)
Requires-Dist: paho-mqtt (==1.4.0)
Requires-Dist: pydbus (==0.6.0)
Requires-Dist: wirepas-messaging (==1.2.0)
